MANIFEST.in
README.md
VERSION
setup.py
cbra/package.json
cbra.egg-info/PKG-INFO
cbra.egg-info/SOURCES.txt
cbra.egg-info/dependency_links.txt
cbra.egg-info/entry_points.txt
cbra.egg-info/requires.txt
cbra.egg-info/top_level.txt
cbra/core/__init__.py
cbra/core/application.py
cbra/core/conf.py
cbra/core/endpoint.py
cbra/core/endpointtype.py
cbra/core/optionsrequesthandler.py
cbra/core/package.json
cbra/core/requesthandler.py
cbra/core/secretkey.py
cbra/core/utils.py
cbra/core/iam/__init__.py
cbra/core/iam/authenticatedcontext.py
cbra/core/iam/authenticationservice.py
cbra/core/iam/authorizationcontextfactory.py
cbra/core/iam/isubjectrepository.py
cbra/core/iam/principalhasher.py
cbra/core/iam/subject.py
cbra/core/iam/subjectresolver.py
cbra/core/iam/models/__init__.py
cbra/core/iam/models/emailprincipal.py
cbra/core/iam/models/externalprincipal.py
cbra/core/iam/models/principal.py
cbra/core/iam/models/principalmodel.py
cbra/core/iam/models/publicidentifierprincipal.py
cbra/core/iam/models/subject.py
cbra/core/iam/services/__init__.py
cbra/core/iam/services/useronboarding.py
cbra/core/iam/types/__init__.py
cbra/core/iam/types/isubjectrepository.py
cbra/core/iam/types/iuseronboardingservice.py
cbra/core/iam/types/principal.py
cbra/core/iam/types/principaltype.py
cbra/core/iam/types/publicidentifier.py
cbra/core/iam/types/subject.py
cbra/core/ioc/__init__.py
cbra/core/ioc/config.py
cbra/core/ioc/container.py
cbra/core/ioc/dependency.py
cbra/core/ioc/dependencynotsatisfied.py
cbra/core/ioc/inheriteddependencydecorator.py
cbra/core/ioc/injected.py
cbra/core/ioc/instance.py
cbra/core/ioc/loader.py
cbra/core/ioc/requirement.py
cbra/core/ioc/setting_.py
cbra/core/ioc/test/__init__.py
cbra/core/params/__init__.py
cbra/core/resource/__init__.py
cbra/core/resource/collection.py
cbra/core/resource/collectionaction.py
cbra/core/resource/create.py
cbra/core/resource/createaction.py
cbra/core/resource/customaction.py
cbra/core/resource/delete.py
cbra/core/resource/deleteaction.py
cbra/core/resource/detail.py
cbra/core/resource/detailaction.py
cbra/core/resource/iresource.py
cbra/core/resource/listaction.py
cbra/core/resource/persister.py
