Metadata-Version: 2.1
Name: cbra
Version: 1.1.10
Summary: A class-based REStful API framework built on FastAPI
Home-page: https://docs.cochise.io/python/cbra/latest
Author: Cochise Ruhulessin
Author-email: cochiseruhulessin@gmail.com
Classifier: Development Status :: 4 - Beta
Classifier: Environment :: Console
Classifier: Environment :: Web Environment
Classifier: Intended Audience :: Developers
Classifier: License :: Other/Proprietary License
Classifier: Operating System :: POSIX
Classifier: Operating System :: POSIX :: Linux
Classifier: Programming Language :: Python :: 3.10
Classifier: Programming Language :: Python :: 3.11
Classifier: Programming Language :: Python :: 3 :: Only
Classifier: Topic :: Internet
Classifier: Topic :: Internet :: WWW/HTTP :: Session
Classifier: Topic :: Software Development :: Libraries
Provides-Extra: all
Provides-Extra: google
Provides-Extra: gunicorn
